pulumi_azuredevops/__init__.py
pulumi_azuredevops/_inputs.py
pulumi_azuredevops/_utilities.py
pulumi_azuredevops/area_permissions.py
pulumi_azuredevops/branch_policy_auto_reviewers.py
pulumi_azuredevops/branch_policy_build_validation.py
pulumi_azuredevops/branch_policy_comment_resolution.py
pulumi_azuredevops/branch_policy_merge_types.py
pulumi_azuredevops/branch_policy_min_reviewers.py
pulumi_azuredevops/branch_policy_status_check.py
pulumi_azuredevops/branch_policy_work_item_linking.py
pulumi_azuredevops/build_definition.py
pulumi_azuredevops/build_definition_permissions.py
pulumi_azuredevops/build_folder.py
pulumi_azuredevops/build_folder_permissions.py
pulumi_azuredevops/check_approval.py
pulumi_azuredevops/check_branch_control.py
pulumi_azuredevops/check_business_hours.py
pulumi_azuredevops/check_exclusive_lock.py
pulumi_azuredevops/check_required_template.py
pulumi_azuredevops/check_rest_api.py
pulumi_azuredevops/dashboard.py
pulumi_azuredevops/elastic_pool.py
pulumi_azuredevops/environment.py
pulumi_azuredevops/environment_resource_kubernetes.py
pulumi_azuredevops/extension.py
pulumi_azuredevops/feed.py
pulumi_azuredevops/feed_permission.py
pulumi_azuredevops/feed_retention_policy.py
pulumi_azuredevops/get_agent_queue.py
pulumi_azuredevops/get_area.py
pulumi_azuredevops/get_build_definition.py
pulumi_azuredevops/get_client_config.py
pulumi_azuredevops/get_descriptor.py
pulumi_azuredevops/get_environment.py
pulumi_azuredevops/get_feed.py
pulumi_azuredevops/get_git_repository.py
pulumi_azuredevops/get_git_repository_file.py
pulumi_azuredevops/get_group.py
pulumi_azuredevops/get_group_membership.py
pulumi_azuredevops/get_groups.py
pulumi_azuredevops/get_identity_group.py
pulumi_azuredevops/get_identity_groups.py
pulumi_azuredevops/get_identity_users.py
pulumi_azuredevops/get_iteration.py
pulumi_azuredevops/get_pool.py
pulumi_azuredevops/get_pools.py
pulumi_azuredevops/get_project.py
pulumi_azuredevops/get_projects.py
pulumi_azuredevops/get_repositories.py
pulumi_azuredevops-3.10.2.dist-info/METADATA
pulumi_azuredevops-3.10.2.dist-info/WHEEL
pulumi_azuredevops-3.10.2.dist-info/top_level.txt
pulumi_azuredevops-3.10.2.dist-info/RECORD
